[
	{
		"inputs": [
			{
				"internalType": "uint256",
				"name": "_royalty",
				"type": "uint256"
			}
		],
		"stateMutability": "nonpayable",
		"type": "constructor"
	},
	{
		"inputs": [
			{
				"internalType": "uint256",
				"name": "_index",
				"type": "uint256"
			}
		],
		"name": "buyCanvas",
		"outputs": [],
		"stateMutability": "nonpayable",
		"type": "function"
	},
	{
		"inputs": [
			{
				"internalType": "string",
				"name": "_name",
				"type": "string"
			},
			{
				"internalType": "bytes32[6]",
				"name": "_pixels",
				"type": "bytes32[6]"
			},
			{
				"internalType": "string",
				"name": "_description",
				"type": "string"
			},
			{
				"internalType": "uint256",
				"name": "_price",
				"type": "uint256"
			}
		],
		"name": "createCanvas",
		"outputs": [],
		"stateMutability": "nonpayable",
		"type": "function"
	},
	{
		"inputs": [],
		"name": "getCanvasLength",
		"outputs": [
			{
				"internalType": "uint256",
				"name": "",
				"type": "uint256"
			}
		],
		"stateMutability": "view",
		"type": "function"
	},
	{
		"inputs": [],
		"name": "owner",
		"outputs": [
			{
				"internalType": "address",
				"name": "",
				"type": "address"
			}
		],
		"stateMutability": "view",
		"type": "function"
	},
	{
		"inputs": [
			{
				"internalType": "uint256",
				"name": "_index",
				"type": "uint256"
			}
		],
		"name": "readCanvas",
		"outputs": [
			{
				"internalType": "string",
				"name": "",
				"type": "string"
			},
			{
				"internalType": "address",
				"name": "",
				"type": "address"
			},
			{
				"internalType": "bytes32[6]",
				"name": "",
				"type": "bytes32[6]"
			},
			{
				"internalType": "address",
				"name": "",
				"type": "address"
			},
			{
				"internalType": "string",
				"name": "",
				"type": "string"
			},
			{
				"internalType": "uint256",
				"name": "",
				"type": "uint256"
			}
		],
		"stateMutability": "view",
		"type": "function"
	},
	{
		"inputs": [],
		"name": "royalty",
		"outputs": [
			{
				"internalType": "uint256",
				"name": "",
				"type": "uint256"
			}
		],
		"stateMutability": "view",
		"type": "function"
	},
	{
		"inputs": [
			{
				"internalType": "uint256",
				"name": "_index",
				"type": "uint256"
			},
			{
				"internalType": "uint256",
				"name": "_price",
				"type": "uint256"
			}
		],
		"name": "setPrice",
		"outputs": [],
		"stateMutability": "nonpayable",
		"type": "function"
	},
	{
		"inputs": [
			{
				"internalType": "uint256",
				"name": "_royalty",
				"type": "uint256"
			}
		],
		"name": "setRoyalty",
		"outputs": [],
		"stateMutability": "nonpayable",
		"type": "function"
	}
]